adafruit_lidarlite.py
adafruit_circuitpython_lidarlite-1.3.12.dist-info/licenses/LICENSE
adafruit_circuitpython_lidarlite-1.3.12.dist-info/METADATA
adafruit_circuitpython_lidarlite-1.3.12.dist-info/WHEEL
adafruit_circuitpython_lidarlite-1.3.12.dist-info/top_level.txt
adafruit_circuitpython_lidarlite-1.3.12.dist-info/RECORD
