Metadata-Version: 2.4
Name: adafruit-circuitpython-lidarlite
Version: 1.3.12
Summary: A CircuitPython & Python library for Garmin LIDAR Lite sensors over I2C.
Author-email: Adafruit Industries <circuitpython@adafruit.com>
License: MIT
Project-URL: Homepage, https://github.com/adafruit/Adafruit_CircuitPython_LIDARLite
Keywords: adafruit,lidarlite,lidar,garmin,i2c,hardware,sensor,micropython,circuitpython
Classifier: Intended Audience :: Developers
Classifier: Topic :: Software Development :: Libraries
Classifier: Topic :: Software Development :: Embedded Systems
Classifier: Topic :: System :: Hardware
Classifier: License :: OSI Approved :: MIT License
Classifier: Programming Language :: Python :: 3
License-File: LICENSE
Requires-Dist: Adafruit-Blinka
Requires-Dist: adafruit-circuitpython-busdevice
Provides-Extra: optional
Dynamic: license-file
